anapi/__init__.py
anapi-2.0.1.dist-info/LICENSE
anapi-2.0.1.dist-info/METADATA
anapi-2.0.1.dist-info/WHEEL
anapi-2.0.1.dist-info/top_level.txt
anapi-2.0.1.dist-info/RECORD
