Metadata-Version: 2.1
Name: anapi
Version: 2.0.1
Summary: AnAPI lib
Home-page: https://ai.wispace.ru/
Author: WiSpace
Author-email: wiforumit@gmail.com
Requires-Python: >=3.6
License-File: LICENSE
